{
    "m1476816490837": {
        "userId": "u123",
        "text": "dssfd",
        "ts": 1476816490837,
        "id": "m1476816490837"
    },
    "m1476816492673": {
        "userId": "u123",
        "text": "sdf",
        "ts": 1476816492673,
        "id": "m1476816492673"
    },
    "m1476816495154": {
        "userId": "u123",
        "text": "sdfsdf",
        "ts": 1476816495154,
        "id": "m1476816495154"
    },
    "m1476816495724": {
        "userId": "u123",
        "text": "sd",
        "ts": 1476816495724,
        "id": "m1476816495724"
    },
    "m1476816497270": {
        "userId": "u123",
        "text": "sdfsdf",
        "ts": 1476816497270,
        "id": "m1476816497270"
    },
    "m1476816499037": {
        "userId": "u123",
        "text": "dsf",
        "ts": 1476816499037,
        "id": "m1476816499037"
    },
    "m1476816500666": {
        "userId": "u123",
        "text": "sdfsd",
        "ts": 1476816500666,
        "id": "m1476816500666"
    },
    "m1476816503600": {
        "userId": "u123",
        "text": "sdfdsf",
        "ts": 1476816503600,
        "id": "m1476816503600"
    },
    "m1476816505766": {
        "userId": "u123",
        "text": "sdfsdf",
        "ts": 1476816505766,
        "id": "m1476816505766"
    },
    "m1476816508524": {
        "userId": "u123",
        "text": "sdfsfd",
        "ts": 1476816508524,
        "id": "m1476816508524"
    },
    "m1476816510784": {
        "userId": "u123",
        "text": "sdfs",
        "ts": 1476816510784,
        "id": "m1476816510784"
    },
    "m1476816511419": {
        "userId": "u123",
        "text": "sdfsd",
        "ts": 1476816511419,
        "id": "m1476816511419"
    },
    "m1476816511702": {
        "userId": "u123",
        "text": "df",
        "ts": 1476816511702,
        "id": "m1476816511702"
    },
    "m1476816511931": {
        "userId": "u123",
        "text": "sd",
        "ts": 1476816511931,
        "id": "m1476816511931"
    },
    "m1476816512099": {
        "userId": "u123",
        "text": "f",
        "ts": 1476816512099,
        "id": "m1476816512099"
    },
    "m1476816512294": {
        "userId": "u123",
        "text": "sd",
        "ts": 1476816512294,
        "id": "m1476816512294"
    },
    "m1476816512498": {
        "userId": "u123",
        "text": "dsf",
        "ts": 1476816512498,
        "id": "m1476816512498"
    },
    "m1476816512845": {
        "userId": "u123",
        "text": "dsf",
        "ts": 1476816512845,
        "id": "m1476816512845"
    },
    "m1476816513005": {
        "userId": "u123",
        "text": "f",
        "ts": 1476816513005,
        "id": "m1476816513005"
    },
    "m1476816513189": {
        "userId": "u123",
        "text": "ds",
        "ts": 1476816513189,
        "id": "m1476816513189"
    },
    "m1476816513396": {
        "userId": "u123",
        "text": "sfd",
        "ts": 1476816513396,
        "id": "m1476816513396"
    },
    "m1476816513571": {
        "userId": "u123",
        "text": "fds",
        "ts": 1476816513571,
        "id": "m1476816513571"
    },
    "m1476816513772": {
        "userId": "u123",
        "text": "sfd",
        "ts": 1476816513772,
        "id": "m1476816513772"
    },
    "m1476816513979": {
        "userId": "u123",
        "text": "sdf",
        "ts": 1476816513979,
        "id": "m1476816513979"
    },
    "m1476816514155": {
        "userId": "u123",
        "text": "fds",
        "ts": 1476816514155,
        "id": "m1476816514155"
    },
    "m1476816514322": {
        "userId": "u123",
        "text": "sfd",
        "ts": 1476816514322,
        "id": "m1476816514322"
    },
    "m1476816515241": {
        "userId": "u123",
        "text": "fdslfdkngk;fdg",
        "ts": 1476816515241,
        "id": "m1476816515241"
    },
    "m1476816515428": {
        "userId": "u123",
        "text": "fg",
        "ts": 1476816515428,
        "id": "m1476816515428"
    },
    "m1476816515619": {
        "userId": "u123",
        "text": "gh",
        "ts": 1476816515619,
        "id": "m1476816515619"
    },
    "m1476816515776": {
        "userId": "u123",
        "text": "hg",
        "ts": 1476816515776,
        "id": "m1476816515776"
    },
    "m1476816515924": {
        "userId": "u123",
        "text": "gh",
        "ts": 1476816515924,
        "id": "m1476816515924"
    },
    "m1476816516632": {
        "userId": "u123",
        "text": "gh",
        "ts": 1476816516632,
        "id": "m1476816516632"
    },
    "m1476816516832": {
        "userId": "u123",
        "text": "gh",
        "ts": 1476816516832,
        "id": "m1476816516832"
    },
    "m1476816517016": {
        "userId": "u123",
        "text": "hg",
        "ts": 1476816517016,
        "id": "m1476816517016"
    },
    "m1476816517246": {
        "userId": "u123",
        "text": "g",
        "ts": 1476816517246,
        "id": "m1476816517246"
    },
    "m1476816517450": {
        "userId": "u123",
        "text": "gf",
        "ts": 1476816517450,
        "id": "m1476816517450"
    },
    "m1476816517654": {
        "userId": "u123",
        "text": "gf",
        "ts": 1476816517654,
        "id": "m1476816517654"
    },
    "m1476816517782": {
        "userId": "u123",
        "text": "fg",
        "ts": 1476816517782,
        "id": "m1476816517782"
    },
    "m1476816518167": {
        "userId": "u123",
        "text": "d",
        "ts": 1476816518167,
        "id": "m1476816518167"
    },
    "m1476816518372": {
        "userId": "u123",
        "text": "dsds",
        "ts": 1476816518372,
        "id": "m1476816518372"
    },
    "m1476816518787": {
        "userId": "u123",
        "text": "ds",
        "ts": 1476816518787,
        "id": "m1476816518787"
    },
    "m1476816519015": {
        "userId": "u123",
        "text": "das",
        "ts": 1476816519015,
        "id": "m1476816519015"
    },
    "m1476816519229": {
        "userId": "u123",
        "text": "sad",
        "ts": 1476816519229,
        "id": "m1476816519229"
    },
    "m1476816519465": {
        "userId": "u123",
        "text": "sad",
        "ts": 1476816519465,
        "id": "m1476816519465"
    },
    "m1476816519680": {
        "userId": "u123",
        "text": "das",
        "ts": 1476816519680,
        "id": "m1476816519680"
    },
    "m1476816519878": {
        "userId": "u123",
        "text": "d",
        "ts": 1476816519878,
        "id": "m1476816519878"
    },
    "m1476816520170": {
        "userId": "u123",
        "text": "d",
        "ts": 1476816520170,
        "id": "m1476816520170"
    },
    "m1476816520373": {
        "userId": "u123",
        "text": "d",
        "ts": 1476816520373,
        "id": "m1476816520373"
    },
    "m1476816520576": {
        "userId": "u123",
        "text": "d",
        "ts": 1476816520576,
        "id": "m1476816520576"
    },
    "m1476816520743": {
        "userId": "u123",
        "text": "d",
        "ts": 1476816520743,
        "id": "m1476816520743"
    },
    "m1476816520896": {
        "userId": "u123",
        "text": "d",
        "ts": 1476816520896,
        "id": "m1476816520896"
    },
    "m1476816521068": {
        "userId": "u123",
        "text": "d",
        "ts": 1476816521068,
        "id": "m1476816521068"
    },
    "m1476816521239": {
        "userId": "u123",
        "text": "d",
        "ts": 1476816521239,
        "id": "m1476816521239"
    },
    "m1476816521422": {
        "userId": "u123",
        "text": "d",
        "ts": 1476816521422,
        "id": "m1476816521422"
    },
    "m1476816521603": {
        "userId": "u123",
        "text": "d",
        "ts": 1476816521603,
        "id": "m1476816521603"
    },
    "m1476816521820": {
        "userId": "u123",
        "text": "d",
        "ts": 1476816521820,
        "id": "m1476816521820"
    },
    "m1476816522014": {
        "userId": "u123",
        "text": "f",
        "ts": 1476816522014,
        "id": "m1476816522014"
    },
    "m1476816522205": {
        "userId": "u123",
        "text": "g",
        "ts": 1476816522205,
        "id": "m1476816522205"
    },
    "m1476816522431": {
        "userId": "u123",
        "text": "h",
        "ts": 1476816522431,
        "id": "m1476816522431"
    },
    "m1476816522615": {
        "userId": "u123",
        "text": "j",
        "ts": 1476816522615,
        "id": "m1476816522615"
    },
    "m1476816522823": {
        "userId": "u123",
        "text": "kj",
        "ts": 1476816522823,
        "id": "m1476816522823"
    },
    "m1476816523028": {
        "userId": "u123",
        "text": "k",
        "ts": 1476816523028,
        "id": "m1476816523028"
    },
    "m1476816523234": {
        "userId": "u123",
        "text": "lk",
        "ts": 1476816523234,
        "id": "m1476816523234"
    },
    "m1476816523447": {
        "userId": "u123",
        "text": "ds",
        "ts": 1476816523447,
        "id": "m1476816523447"
    },
    "m1476816523692": {
        "userId": "u123",
        "text": "ass",
        "ts": 1476816523692,
        "id": "m1476816523692"
    },
    "m1476816523957": {
        "userId": "u123",
        "text": "a",
        "ts": 1476816523957,
        "id": "m1476816523957"
    },
    "m1476816524202": {
        "userId": "u123",
        "text": "sd",
        "ts": 1476816524202,
        "id": "m1476816524202"
    },
    "m1476816524448": {
        "userId": "u123",
        "text": "dsf",
        "ts": 1476816524448,
        "id": "m1476816524448"
    },
    "m1476816524723": {
        "userId": "u123",
        "text": "fd",
        "ts": 1476816524723,
        "id": "m1476816524723"
    },
    "m1476816524969": {
        "userId": "u123",
        "text": "gf",
        "ts": 1476816524969,
        "id": "m1476816524969"
    },
    "m1476816525219": {
        "userId": "u123",
        "text": "gf",
        "ts": 1476816525219,
        "id": "m1476816525219"
    },
    "m1476816525476": {
        "userId": "u123",
        "text": "gf",
        "ts": 1476816525476,
        "id": "m1476816525476"
    },
    "m1476816525742": {
        "userId": "u123",
        "text": "gf",
        "ts": 1476816525742,
        "id": "m1476816525742"
    },
    "m1476994205850": {
        "userId": "u123",
        "text": "sdfsdf",
        "ts": 1476994205850,
        "id": "m1476994205850"
    }
}